fastpluggy/__init__.py
fastpluggy/fastpluggy.py
fastpluggy/core/__init__.py
fastpluggy/core/base_module_manager.py
fastpluggy/core/config.py
fastpluggy/core/database.py
fastpluggy/core/dependency.py
fastpluggy/core/flash.py
fastpluggy/core/global_registry.py
fastpluggy/core/models.py
fastpluggy/core/module_base.py
fastpluggy/core/plugin_state.py
fastpluggy/core/auth/__init__.py
fastpluggy/core/auth/auth_interface.py
fastpluggy/core/auth/middleware.py
fastpluggy/core/error/__init__.py
fastpluggy/core/error/degraded_mode_handler.py
fastpluggy/core/error/exception.py
fastpluggy/core/menu/__init__.py
fastpluggy/core/menu/decorator.py
fastpluggy/core/menu/menu_manager.py
fastpluggy/core/menu/schema.py
fastpluggy/core/models_tools/__init__.py
fastpluggy/core/models_tools/base.py
fastpluggy/core/models_tools/callable.py
fastpluggy/core/models_tools/pydantic.py
fastpluggy/core/models_tools/shared.py
fastpluggy/core/models_tools/sqlalchemy.py
fastpluggy/core/plugin/__init__.py
fastpluggy/core/plugin/dependency_resolver.py
fastpluggy/core/plugin/repository.py
fastpluggy/core/plugin/service.py
fastpluggy/core/repository/__init__.py
fastpluggy/core/repository/app_settings.py
fastpluggy/core/routers/__init__.py
fastpluggy/core/routers/admin.py
fastpluggy/core/routers/app_static.py
fastpluggy/core/routers/base_module.py
fastpluggy/core/routers/execute.py
fastpluggy/core/routers/home.py
fastpluggy/core/routers/ready.py
fastpluggy/core/routers/settings.py
fastpluggy/core/routers/actions/__init__.py
fastpluggy/core/routers/actions/modules.py
fastpluggy/core/tools/__init__.py
fastpluggy/core/tools/fastapi.py
fastpluggy/core/tools/fs_tools.py
fastpluggy/core/tools/inspect_tools.py
fastpluggy/core/tools/install.py
fastpluggy/core/tools/jinja_tools.py
fastpluggy/core/tools/lock.py
fastpluggy/core/tools/serialize_tools.py
fastpluggy/core/tools/system.py
fastpluggy/core/tools/threads_tools.py
fastpluggy/core/view_builder/__init__.py
fastpluggy/core/view_builder/builder.py
fastpluggy-0.3.51.dist-info/METADATA
fastpluggy-0.3.51.dist-info/WHEEL
fastpluggy-0.3.51.dist-info/top_level.txt
fastpluggy-0.3.51.dist-info/RECORD
