Metadata-Version: 2.4
Name: FastPluggy
Version: 0.3.51
Summary: A FastAPI-based framework with plugin management.
Project-URL: Homepage, https://fastpluggy.xyz
Project-URL: Documentation, https://docs.fastpluggy.xyz
Classifier: Programming Language :: Python :: 3
Classifier: License :: OSI Approved :: MIT License
Classifier: Operating System :: OS Independent
Requires-Python: >=3.10
Requires-Dist: fastapi>=0.115.2
Requires-Dist: starlette
Requires-Dist: python-multipart
Requires-Dist: pydantic<3,>=2
Requires-Dist: pydantic-settings
Requires-Dist: jinja2>=3.1.4
Requires-Dist: sqlalchemy>=2.0.35
Requires-Dist: loguru>=0.7.2
Requires-Dist: httpx>=0.27.2
Requires-Dist: itsdangerous>=2.1.0
Requires-Dist: wtforms>=3.0.0
Requires-Dist: semantic-version
Provides-Extra: toml
Requires-Dist: tomli>=2.0.0; python_version < "3.11" and extra == "toml"
